ipx800/__init__.py
ipx800/ipx800.py
gce_ipx800-0.7.1.dist-info/METADATA
gce_ipx800-0.7.1.dist-info/WHEEL
gce_ipx800-0.7.1.dist-info/licenses/LICENSE
gce_ipx800-0.7.1.dist-info/RECORD
