Metadata-Version: 2.4
Name: gce-ipx800
Version: 0.7.1
Summary: Library to interact with the GCE Electronics IPX800 device
License: Apache-2.0
License-File: LICENSE
Keywords: ipx800,GCE-Electronics,GCE,home-automation
Author: Marc-Aurèle Brothier
Author-email: m@brothier.org
Requires-Python: >=3.9,<4.0
Classifier: License :: OSI Approved :: Apache Software License
Classifier: Operating System :: OS Independent
Classifier: Programming Language :: Python
Classifier: Programming Language :: Python :: 3
Classifier: Programming Language :: Python :: 3.9
Classifier: Programming Language :: Python :: 3.10
Classifier: Programming Language :: Python :: 3.11
Classifier: Programming Language :: Python :: 3.12
Classifier: Programming Language :: Python :: 3.13
Classifier: Programming Language :: Python :: 3.14
Classifier: Topic :: Home Automation
Classifier: Topic :: Scientific/Engineering :: Electronic Design Automation (EDA)
Requires-Dist: requests (>=2.26,<3.0)
Project-URL: Bug Tracker, https://github.com/marcaurele/gce-ipx800/issues
Project-URL: Homepage, https://github.com/marcaurele/gce-ipx800
Project-URL: Repository, https://github.com/marcaurele/gce-ipx800
